Metadata-Version: 2.1
Name: bice
Version: 0.3.5
Summary: Numerical continuation and bifurcation package
Home-page: UNKNOWN
Author: Simon Hartmann
Author-email: s.hartmann@wwu.de
License: MIT
Platform: UNKNOWN
